{
  "predictedWinner": "Red",
  "redTeams": [
    28036,
    27584
  ],
  "blueTeams": [
    22302,
    27587
  ],
  "actualWinner": "Red",
  "pointBreakdown": {
    "redData": {
      "redScore": 19,
      "redPenaltyFreeScore": 19,
      "redAuto": 5,
      "redTeleOp": 14,
      "redEndgame": null
    },
    "blueData": {
      "blueScore": 18,
      "bluePenaltyFreeScore": 18,
      "blueAuto": 0,
      "blueTeleOp": 18,
      "blueEndgame": null
    }
  },
  "predictedScores": {
    "redEPA": 24.079533717449983,
    "redAutonEPA": 4.631778892735744,
    "redTeleOpEPA": 19.447754824714238,
    "redEndgameEPA": 0,
    "blueEPA": 20.988612448389375,
    "blueAutonEPA": 3.3175881690984275,
    "blueTeleOpEPA": 17.671024279290947,
    "blueEndgameEPA": 0
  }
}