{
  "predictedWinner": "Blue",
  "redTeams": [
    32066,
    21790
  ],
  "blueTeams": [
    10477,
    31038
  ],
  "actualWinner": "Blue",
  "pointBreakdown": {
    "redData": {
      "redScore": 114,
      "redPenaltyFreeScore": 99,
      "redAuto": 27,
      "redTeleOp": 72,
      "redEndgame": 0
    },
    "blueData": {
      "blueScore": 165,
      "bluePenaltyFreeScore": 155,
      "blueAuto": 46,
      "blueTeleOp": 99,
      "blueEndgame": 10
    }
  },
  "predictedScores": {
    "redEPA": 68.61554611183146,
    "redAutonEPA": 24.096709171061587,
    "redTeleOpEPA": 38.43495249270925,
    "redEndgameEPA": 6.0838844480606245,
    "blueEPA": 181.32908279791494,
    "blueAutonEPA": 48.280942321745485,
    "blueTeleOpEPA": 124.59843127918937,
    "blueEndgameEPA": 8.449709196980091
  }
}