{
  "predictedWinner": "Blue",
  "redTeams": [
    12294,
    18472
  ],
  "blueTeams": [
    13643,
    12303
  ],
  "actualWinner": "Red",
  "pointBreakdown": {
    "redData": {
      "redScore": 168,
      "redPenaltyFreeScore": 168,
      "redAuto": 32,
      "redTeleOp": 56,
      "redEndgame": 80
    },
    "blueData": {
      "blueScore": 150,
      "bluePenaltyFreeScore": 150,
      "blueAuto": 68,
      "blueTeleOp": 22,
      "blueEndgame": 60
    }
  },
  "predictedScores": {
    "redEPA": 51.1003985246931,
    "redAutonEPA": 34.07548912139873,
    "redTeleOpEPA": -24.309535279480507,
    "redEndgameEPA": 41.33444468277487,
    "blueEPA": 97.9421305450404,
    "blueAutonEPA": 42.160251972509386,
    "blueTeleOpEPA": -4.605139844445027,
    "blueEndgameEPA": 60.38701841697604
  }
}