{
  "predictedWinner": "Red",
  "redTeams": [
    8142,
    19770
  ],
  "blueTeams": [
    9297,
    12362
  ],
  "actualWinner": "Blue",
  "pointBreakdown": {
    "redData": {
      "redScore": 65,
      "redPenaltyFreeScore": 35,
      "redAuto": 30,
      "redTeleOp": -40,
      "redEndgame": 45
    },
    "blueData": {
      "blueScore": 82,
      "bluePenaltyFreeScore": 82,
      "blueAuto": 22,
      "blueTeleOp": 24,
      "blueEndgame": 36
    }
  },
  "predictedScores": {
    "redEPA": 62.92054871846787,
    "redAutonEPA": 18.133894401969428,
    "redTeleOpEPA": 1.5271663690245205,
    "redEndgameEPA": 43.25948794747392,
    "blueEPA": 21.030073651526354,
    "blueAutonEPA": -0.806613397359594,
    "blueTeleOpEPA": -18.204287485083128,
    "blueEndgameEPA": 40.04097453396908
  }
}