{"matches":[{"actualStartTime":"2024-11-23T11:05:56.865","description":"Qualification 1","tournamentLevel":"QUALIFICATION","series":0,"matchNumber":1,"scoreRedFinal":13,"scoreRedFoul":0,"scoreRedAuto":0,"scoreBlueFinal":181,"scoreBlueFoul":0,"scoreBlueAuto":41,"postResultTime":"2024-11-23T11:10:44.664","teams":[{"teamNumber":23027,"station":"Red1","dq":false,"onField":true},{"teamNumber":11317,"station":"Red2","dq":false,"onField":true},{"teamNumber":11228,"station":"Blue1","dq":false,"onField":true},{"teamNumber":10538,"station":"Blue2","dq":false,"onField":true}],"modifiedOn":"2024-11-23T23:34:18.881"},{"actualStartTime":"2024-11-23T11:11:17.01","description":"Qualification 2","tournamentLevel":"QUALIFICATION","series":0,"matchNumber":2,"scoreRedFinal":125,"scoreRedFoul":0,"scoreRedAuto":28,"scoreBlueFinal":103,"scoreBlueFoul":0,"scoreBlueAuto":21,"postResultTime":"2024-11-23T11:15:20.395","teams":[{"teamNumber":20245,"station":"Red1","dq":false,"onField":true},{"teamNumber":15339,"station":"Red2","dq":false,"onField":true},{"teamNumber":5385,"station":"Blue1","dq":false,"onField":true},{"teamNumber":22885,"station":"Blue2","dq":false,"onField":true}],"modifiedOn":"2024-11-23T23:34:18.766"},{"actualStartTime":"2024-11-23T11:16:31.667","description":"Qualification 3","tournamentLevel":"QUALIFICATION","series":0,"matchNumber":3,"scoreRedFinal":48,"scoreRedFoul":5,"scoreRedAuto":0,"scoreBlueFinal":50,"scoreBlueFoul":0,"scoreBlueAuto":10,"postResultTime":"2024-11-23T11:20:39.651","teams":[{"teamNumber":14933,"station":"Red2","dq":false,"onField":true},{"teamNumber":8932,"station":"Red1","dq":false,"onField":true},{"teamNumber":8529,"station":"Blue1","dq":false,"onField":true},{"teamNumber":5980,"station":"Blue2","dq":false,"onField":true}],"modifiedOn":"2024-11-23T23:34:19.146"},{"actualStartTime":"2024-11-23T11:22:04.659","description":"Qualification 4","tournamentLevel":"QUALIFICATION","series":0,"matchNumber":4,"scoreRedFinal":81,"scoreRedFoul":0,"scoreRedAuto":13,"scoreBlueFinal":33,"scoreBlueFoul":0,"scoreBlueAuto":0,"postResultTime":"2024-11-23T11:26:29.216","teams":[{"teamNumber":20863,"station":"Blue2","dq":false,"onField":true},{"teamNumber":22154,"station":"Blue1","dq":false,"onField":true},{"teamNumber":6283,"station":"Red2","dq":false,"onField":true},{"teamNumber":17283,"station":"Red1","dq":false,"onField":true}],"modifiedOn":"2024-11-23T23:34:19.136"},{"actualStartTime":"2024-11-23T11:27:05.119","description":"Qualification 5","tournamentLevel":"QUALIFICATION","series":0,"matchNumber":5,"scoreRedFinal":36,"scoreRedFoul":0,"scoreRedAuto":0,"scoreBlueFinal":144,"scoreBlueFoul":0,"scoreBlueAuto":34,"postResultTime":"2024-11-23T11:31:32.966","teams":[{"teamNumber":11254,"station":"Red1","dq":false,"onField":true},{"teamNumber":5290,"station":"Blue2","dq":false,"onField":true},{"teamNumber":11531,"station":"Blue1","dq":false,"onField":true},{"teamNumber":24371,"station":"Red2","dq":false,"onField":true}],"modifiedOn":"2024-11-23T23:34:19.098"},{"actualStartTime":"2024-11-23T11:32:03.182","description":"Qualification 6","tournamentLevel":"QUALIFICATION","series":0,"matchNumber":6,"scoreRedFinal":92,"scoreRedFoul":0,"scoreRedAuto":13,"scoreBlueFinal":108,"scoreBlueFoul":0,"scoreBlueAuto":19,"postResultTime":"2024-11-23T11:36:51.771","teams":[{"teamNumber":23856,"station":"Blue2","dq":false,"onField":true},{"teamNumber":15815,"station":"Blue1","dq":false,"onField":true},{"teamNumber":18092,"station":"Red2","dq":false,"onField":true},{"teamNumber":20862,"station":"Red1","dq":false,"onField":true}],"modifiedOn":"2024-11-23T23:34:19.05"},{"actualStartTime":"2024-11-23T11:37:31.784","description":"Qualification 7","tournamentLevel":"QUALIFICATION","series":0,"matchNumber":7,"scoreRedFinal":22,"scoreRedFoul":0,"scoreRedAuto":10,"scoreBlueFinal":92,"scoreBlueFoul":0,"scoreBlueAuto":13,"postResultTime":"2024-11-23T11:41:28.479","teams":[{"teamNumber":17401,"station":"Red2","dq":false,"onField":true},{"teamNumber":19429,"station":"Red1","dq":false,"onField":true},{"teamNumber":20299,"station":"Blue2","dq":false,"onField":true},{"teamNumber":11266,"station":"Blue1","dq":false,"onField":true}],"modifiedOn":"2024-11-23T23:34:19.021"},{"actualStartTime":"2024-11-23T11:43:59.547","description":"Qualification 8","tournamentLevel":"QUALIFICATION","series":0,"matchNumber":8,"scoreRedFinal":26,"scoreRedFoul":0,"scoreRedAuto":3,"scoreBlueFinal":78,"scoreBlueFoul":0,"scoreBlueAuto":0,"postResultTime":"2024-11-23T11:48:01.544","teams":[{"teamNumber":10180,"station":"Blue2","dq":false,"onField":true},{"teamNumber":11846,"station":"Red1","dq":false,"onField":true},{"teamNumber":8733,"station":"Red2","dq":false,"onField":true},{"teamNumber":15510,"station":"Blue1","dq":false,"onField":true}],"modifiedOn":"2024-11-23T23:34:18.984"},{"actualStartTime":"2024-11-23T11:48:54.623","description":"Qualification 9","tournamentLevel":"QUALIFICATION","series":0,"matchNumber":9,"scoreRedFinal":42,"scoreRedFoul":0,"scoreRedAuto":4,"scoreBlueFinal":165,"scoreBlueFoul":0,"scoreBlueAuto":30,"postResultTime":"2024-11-23T11:54:12.552","teams":[{"teamNumber":8529,"station":"Red2","dq":false,"onField":true},{"teamNumber":27689,"station":"Blue1","dq":false,"onField":true},{"teamNumber":10255,"station":"Blue2","dq":false,"onField":true},{"teamNumber":10031,"station":"Red1","dq":false,"onField":true}],"modifiedOn":"2024-11-23T23:34:18.965"},{"actualStartTime":"2024-11-23T11:54:50.048","description":"Qualification 10","tournamentLevel":"QUALIFICATION","series":0,"matchNumber":10,"scoreRedFinal":108,"scoreRedFoul":0,"scoreRedAuto":19,"scoreBlueFinal":103,"scoreBlueFoul":0,"scoreBlueAuto":29,"postResultTime":"2024-11-23T11:58:31.582","teams":[{"teamNumber":11317,"station":"Blue1","dq":false,"onField":true},{"teamNumber":17283,"station":"Red2","dq":false,"onField":true},{"teamNumber":15815,"station":"Red1","dq":false,"onField":true},{"teamNumber":5385,"station":"Blue2","dq":false,"onField":true}],"modifiedOn":"2024-11-23T23:34:18.947"},{"actualStartTime":"2024-11-23T11:59:44.414","description":"Qualification 11","tournamentLevel":"QUALIFICATION","series":0,"matchNumber":11,"scoreRedFinal":90,"scoreRedFoul":0,"scoreRedAuto":13,"scoreBlueFinal":158,"scoreBlueFoul":0,"scoreBlueAuto":40,"postResultTime":"2024-11-23T12:04:01.525","teams":[{"teamNumber":14933,"station":"Blue1","dq":false,"onField":true},{"teamNumber":20862,"station":"Red1","dq":false,"onField":true},{"teamNumber":19429,"station":"Blue2","dq":false,"onField":true},{"teamNumber":23027,"station":"Red2","dq":false,"onField":true}],"modifiedOn":"2024-11-23T23:34:18.928"},{"actualStartTime":"2024-11-23T12:06:10.374","description":"Qualification 12","tournamentLevel":"QUALIFICATION","series":0,"matchNumber":12,"scoreRedFinal":117,"scoreRedFoul":0,"scoreRedAuto":23,"scoreBlueFinal":37,"scoreBlueFoul":0,"scoreBlueAuto":0,"postResultTime":"2024-11-23T12:12:22.117","teams":[{"teamNumber":23856,"station":"Red1","dq":false,"onField":true},{"teamNumber":24371,"station":"Red2","dq":false,"onField":true},{"teamNumber":17401,"station":"Blue1","dq":false,"onField":true},{"teamNumber":11846,"station":"Blue2","dq":false,"onField":true}],"modifiedOn":"2024-11-23T23:34:18.919"},{"actualStartTime":"2024-11-23T12:13:15.302","description":"Qualification 13","tournamentLevel":"QUALIFICATION","series":0,"matchNumber":13,"scoreRedFinal":237,"scoreRedFoul":15,"scoreRedAuto":47,"scoreBlueFinal":86,"scoreBlueFoul":0,"scoreBlueAuto":16,"postResultTime":"2024-11-23T12:17:40.389","teams":[{"teamNumber":11228,"station":"Red1","dq":false,"onField":true},{"teamNumber":10255,"station":"Red2","dq":false,"onField":true},{"teamNumber":15339,"station":"Blue1","dq":false,"onField":true},{"teamNumber":6283,"station":"Blue2","dq":false,"onField":true}],"modifiedOn":"2024-11-23T23:34:18.91"},{"actualStartTime":"2024-11-23T12:18:59.267","description":"Qualification 14","tournamentLevel":"QUALIFICATION","series":0,"matchNumber":14,"scoreRedFinal":18,"scoreRedFoul":0,"scoreRedAuto":6,"scoreBlueFinal":52,"scoreBlueFoul":0,"scoreBlueAuto":17,"postResultTime":"2024-11-23T12:22:45.874","teams":[{"teamNumber":10031,"station":"Blue2","dq":false,"onField":true},{"teamNumber":11254,"station":"Blue1","dq":false,"onField":true},{"teamNumber":22154,"station":"Red2","dq":false,"onField":true},{"teamNumber":15510,"station":"Red1","dq":false,"onField":true}],"modifiedOn":"2024-11-23T23:34:18.9"},{"actualStartTime":"2024-11-23T12:23:42.213","description":"Qualification 15","tournamentLevel":"QUALIFICATION","series":0,"matchNumber":15,"scoreRedFinal":84,"scoreRedFoul":0,"scoreRedAuto":10,"scoreBlueFinal":99,"scoreBlueFoul":0,"scoreBlueAuto":3,"postResultTime":"2024-11-23T12:27:54.721","teams":[{"teamNumber":5980,"station":"Blue1","dq":false,"onField":true},{"teamNumber":10538,"station":"Blue2","dq":false,"onField":true},{"teamNumber":22885,"station":"Red2","dq":false,"onField":true},{"teamNumber":8733,"station":"Red1","dq":false,"onField":true}],"modifiedOn":"2024-11-23T23:34:18.891"},{"actualStartTime":"2024-11-23T13:00:44.244","description":"Qualification 16","tournamentLevel":"QUALIFICATION","series":0,"matchNumber":16,"scoreRedFinal":163,"scoreRedFoul":0,"scoreRedAuto":13,"scoreBlueFinal":112,"scoreBlueFoul":0,"scoreBlueAuto":15,"postResultTime":"2024-11-23T13:04:53.067","teams":[{"teamNumber":11531,"station":"Blue2","dq":false,"onField":true},{"teamNumber":20245,"station":"Blue1","dq":false,"onField":true},{"teamNumber":11266,"station":"Red2","dq":false,"onField":true},{"teamNumber":10180,"station":"Red1","dq":false,"onField":true}],"modifiedOn":"2024-11-23T23:34:18.872"},{"actualStartTime":"2024-11-23T13:05:32.703","description":"Qualification 17","tournamentLevel":"QUALIFICATION","series":0,"matchNumber":17,"scoreRedFinal":30,"scoreRedFoul":0,"scoreRedAuto":5,"scoreBlueFinal":65,"scoreBlueFoul":0,"scoreBlueAuto":23,"postResultTime":"2024-11-23T13:09:41.512","teams":[{"teamNumber":20299,"station":"Blue1","dq":false,"onField":true},{"teamNumber":27689,"station":"Red2","dq":false,"onField":true},{"teamNumber":8932,"station":"Red1","dq":false,"onField":true},{"teamNumber":5290,"station":"Blue2","dq":false,"onField":true}],"modifiedOn":"2024-11-23T23:34:19.126"},{"actualStartTime":"2024-11-23T13:11:07.447","description":"Qualification 18","tournamentLevel":"QUALIFICATION","series":0,"matchNumber":18,"scoreRedFinal":47,"scoreRedFoul":0,"scoreRedAuto":3,"scoreBlueFinal":206,"scoreBlueFoul":0,"scoreBlueAuto":26,"postResultTime":"2024-11-23T13:15:05.967","teams":[{"teamNumber":10255,"station":"Blue2","dq":false,"onField":true},{"teamNumber":18092,"station":"Blue1","dq":false,"onField":true},{"teamNumber":11317,"station":"Red2","dq":false,"onField":true},{"teamNumber":20863,"station":"Red1","dq":false,"onField":true}],"modifiedOn":"2024-11-23T23:34:18.853"},{"actualStartTime":"2024-11-23T13:15:55.657","description":"Qualification 19","tournamentLevel":"QUALIFICATION","series":0,"matchNumber":19,"scoreRedFinal":161,"scoreRedFoul":0,"scoreRedAuto":33,"scoreBlueFinal":111,"scoreBlueFoul":0,"scoreBlueAuto":13,"postResultTime":"2024-11-23T13:19:41.492","teams":[{"teamNumber":15510,"station":"Red1","dq":false,"onField":true},{"teamNumber":11228,"station":"Red2","dq":false,"onField":true},{"teamNumber":22885,"station":"Blue1","dq":false,"onField":true},{"teamNumber":20862,"station":"Blue2","dq":false,"onField":true}],"modifiedOn":"2024-11-23T23:34:19.107"},{"actualStartTime":"2024-11-23T13:20:55.055","description":"Qualification 20","tournamentLevel":"QUALIFICATION","series":0,"matchNumber":20,"scoreRedFinal":61,"scoreRedFoul":0,"scoreRedAuto":13,"scoreBlueFinal":113,"scoreBlueFoul":0,"scoreBlueAuto":13,"postResultTime":"2024-11-23T13:24:30.633","teams":[{"teamNumber":8733,"station":"Blue2","dq":false,"onField":true},{"teamNumber":11531,"station":"Blue1","dq":false,"onField":true},{"teamNumber":17283,"station":"Red2","dq":false,"onField":true},{"teamNumber":8529,"station":"Red1","dq":false,"onField":true}],"modifiedOn":"2024-11-23T23:34:18.834"},{"actualStartTime":"2024-11-23T13:27:19.102","description":"Qualification 21","tournamentLevel":"QUALIFICATION","series":0,"matchNumber":21,"scoreRedFinal":45,"scoreRedFoul":0,"scoreRedAuto":12,"scoreBlueFinal":41,"scoreBlueFoul":0,"scoreBlueAuto":6,"postResultTime":"2024-11-23T13:31:56.439","teams":[{"teamNumber":20245,"station":"Blue2","dq":false,"onField":true},{"teamNumber":27689,"station":"Blue1","dq":false,"onField":true},{"teamNumber":23027,"station":"Red2","dq":false,"onField":true},{"teamNumber":17401,"station":"Red1","dq":false,"onField":true}],"modifiedOn":"2024-11-23T23:34:19.079"},{"actualStartTime":"2024-11-23T13:33:47.6","description":"Qualification 22","tournamentLevel":"QUALIFICATION","series":0,"matchNumber":22,"scoreRedFinal":201,"scoreRedFoul":0,"scoreRedAuto":29,"scoreBlueFinal":80,"scoreBlueFoul":30,"scoreBlueAuto":15,"postResultTime":"2024-11-23T13:38:49.732","teams":[{"teamNumber":20863,"station":"Red1","dq":false,"onField":true},{"teamNumber":5385,"station":"Red2","dq":false,"onField":true},{"teamNumber":8932,"station":"Blue1","dq":false,"onField":true},{"teamNumber":11266,"station":"Blue2","dq":false,"onField":true}],"modifiedOn":"2024-11-23T23:34:18.815"},{"actualStartTime":"2024-11-23T13:39:25.176","description":"Qualification 23","tournamentLevel":"QUALIFICATION","series":0,"matchNumber":23,"scoreRedFinal":112,"scoreRedFoul":0,"scoreRedAuto":24,"scoreBlueFinal":129,"scoreBlueFoul":0,"scoreBlueAuto":21,"postResultTime":"2024-11-23T13:43:27.534","teams":[{"teamNumber":11254,"station":"Blue2","dq":false,"onField":true},{"teamNumber":10180,"station":"Blue1","dq":false,"onField":true},{"teamNumber":15815,"station":"Red2","dq":false,"onField":true},{"teamNumber":15339,"station":"Red1","dq":false,"onField":true}],"modifiedOn":"2024-11-23T23:34:19.059"},{"actualStartTime":"2024-11-23T13:44:19.171","description":"Qualification 24","tournamentLevel":"QUALIFICATION","series":0,"matchNumber":24,"scoreRedFinal":54,"scoreRedFoul":0,"scoreRedAuto":11,"scoreBlueFinal":67,"scoreBlueFoul":0,"scoreBlueAuto":15,"postResultTime":"2024-11-23T13:48:53.808","teams":[{"teamNumber":11846,"station":"Red2","dq":false,"onField":true},{"teamNumber":5290,"station":"Red1","dq":false,"onField":true},{"teamNumber":6283,"station":"Blue1","dq":false,"onField":true},{"teamNumber":10031,"station":"Blue2","dq":false,"onField":true}],"modifiedOn":"2024-11-23T23:34:18.806"},{"actualStartTime":"2024-11-23T13:51:17.647","description":"Qualification 25","tournamentLevel":"QUALIFICATION","series":0,"matchNumber":25,"scoreRedFinal":72,"scoreRedFoul":0,"scoreRedAuto":13,"scoreBlueFinal":102,"scoreBlueFoul":0,"scoreBlueAuto":10,"postResultTime":"2024-11-23T13:55:07.437","teams":[{"teamNumber":14933,"station":"Blue2","dq":false,"onField":true},{"teamNumber":24371,"station":"Blue1","dq":false,"onField":true},{"teamNumber":18092,"station":"Red2","dq":false,"onField":true},{"teamNumber":20299,"station":"Red1","dq":false,"onField":true}],"modifiedOn":"2024-11-23T23:34:19.04"},{"actualStartTime":"2024-11-23T13:57:14.854","description":"Qualification 26","tournamentLevel":"QUALIFICATION","series":0,"matchNumber":26,"scoreRedFinal":96,"scoreRedFoul":0,"scoreRedAuto":12,"scoreBlueFinal":103,"scoreBlueFoul":0,"scoreBlueAuto":30,"postResultTime":"2024-11-23T14:01:01.169","teams":[{"teamNumber":23856,"station":"Red2","dq":false,"onField":true},{"teamNumber":19429,"station":"Blue2","dq":false,"onField":true},{"teamNumber":22154,"station":"Blue1","dq":false,"onField":true},{"teamNumber":10538,"station":"Red1","dq":false,"onField":true}],"modifiedOn":"2024-11-23T23:34:18.797"},{"actualStartTime":"2024-11-23T14:01:37.101","description":"Qualification 27","tournamentLevel":"QUALIFICATION","series":0,"matchNumber":27,"scoreRedFinal":42,"scoreRedFoul":0,"scoreRedAuto":3,"scoreBlueFinal":183,"scoreBlueFoul":0,"scoreBlueAuto":39,"postResultTime":"2024-11-23T14:05:25.674","teams":[{"teamNumber":15815,"station":"Blue2","dq":false,"onField":true},{"teamNumber":10255,"station":"Blue1","dq":false,"onField":true},{"teamNumber":15510,"station":"Red2","dq":false,"onField":true},{"teamNumber":5980,"station":"Red1","dq":false,"onField":true}],"modifiedOn":"2024-11-23T23:34:19.031"},{"actualStartTime":"2024-11-23T14:06:05.836","description":"Qualification 28","tournamentLevel":"QUALIFICATION","series":0,"matchNumber":28,"scoreRedFinal":103,"scoreRedFoul":5,"scoreRedAuto":13,"scoreBlueFinal":45,"scoreBlueFoul":0,"scoreBlueAuto":3,"postResultTime":"2024-11-23T14:10:09.865","teams":[{"teamNumber":11266,"station":"Red1","dq":false,"onField":true},{"teamNumber":20862,"station":"Red2","dq":false,"onField":true},{"teamNumber":11317,"station":"Blue1","dq":false,"onField":true},{"teamNumber":8733,"station":"Blue2","dq":false,"onField":true}],"modifiedOn":"2024-11-23T23:34:18.787"},{"actualStartTime":"2024-11-23T14:13:14.752","description":"Qualification 29","tournamentLevel":"QUALIFICATION","series":0,"matchNumber":29,"scoreRedFinal":69,"scoreRedFoul":0,"scoreRedAuto":15,"scoreBlueFinal":97,"scoreBlueFoul":0,"scoreBlueAuto":29,"postResultTime":"2024-11-23T14:17:50.374","teams":[{"teamNumber":18092,"station":"Red1","dq":false,"onField":true},{"teamNumber":8932,"station":"Red2","dq":false,"onField":true},{"teamNumber":23027,"station":"Blue1","dq":false,"onField":true},{"teamNumber":11254,"station":"Blue2","dq":false,"onField":true}],"modifiedOn":"2024-11-23T23:34:19.01"},{"actualStartTime":"2024-11-23T14:19:41.346","description":"Qualification 30","tournamentLevel":"QUALIFICATION","series":0,"matchNumber":30,"scoreRedFinal":147,"scoreRedFoul":0,"scoreRedAuto":24,"scoreBlueFinal":65,"scoreBlueFoul":0,"scoreBlueAuto":11,"postResultTime":"2024-11-23T14:23:36.822","teams":[{"teamNumber":10538,"station":"Red2","dq":false,"onField":true},{"teamNumber":5290,"station":"Red1","dq":false,"onField":true},{"teamNumber":8529,"station":"Blue2","dq":false,"onField":true},{"teamNumber":15339,"station":"Blue1","dq":false,"onField":true}],"modifiedOn":"2024-11-23T23:34:18.777"},{"actualStartTime":"2024-11-23T14:24:37.578","description":"Qualification 31","tournamentLevel":"QUALIFICATION","series":0,"matchNumber":31,"scoreRedFinal":158,"scoreRedFoul":0,"scoreRedAuto":30,"scoreBlueFinal":104,"scoreBlueFoul":0,"scoreBlueAuto":13,"postResultTime":"2024-11-23T14:28:26.18","teams":[{"teamNumber":10180,"station":"Red2","dq":false,"onField":true},{"teamNumber":24371,"station":"Blue1","dq":false,"onField":true},{"teamNumber":17283,"station":"Blue2","dq":false,"onField":true},{"teamNumber":19429,"station":"Red1","dq":false,"onField":true}],"modifiedOn":"2024-11-23T23:34:18.994"},{"actualStartTime":"2024-11-23T14:29:05.449","description":"Qualification 32","tournamentLevel":"QUALIFICATION","series":0,"matchNumber":32,"scoreRedFinal":39,"scoreRedFoul":0,"scoreRedAuto":3,"scoreBlueFinal":78,"scoreBlueFoul":0,"scoreBlueAuto":13,"postResultTime":"2024-11-23T14:33:05.02","teams":[{"teamNumber":17401,"station":"Blue2","dq":false,"onField":true},{"teamNumber":22885,"station":"Blue1","dq":false,"onField":true},{"teamNumber":14933,"station":"Red2","dq":false,"onField":true},{"teamNumber":6283,"station":"Red1","dq":false,"onField":true}],"modifiedOn":"2024-11-23T23:34:18.754"},{"actualStartTime":"2024-11-23T14:33:40.833","description":"Qualification 33","tournamentLevel":"QUALIFICATION","series":0,"matchNumber":33,"scoreRedFinal":130,"scoreRedFoul":0,"scoreRedAuto":26,"scoreBlueFinal":105,"scoreBlueFoul":0,"scoreBlueAuto":15,"postResultTime":"2024-11-23T14:38:58.057","teams":[{"teamNumber":5385,"station":"Red1","dq":false,"onField":true},{"teamNumber":27689,"station":"Blue2","dq":false,"onField":true},{"teamNumber":23856,"station":"Blue1","dq":false,"onField":true},{"teamNumber":11531,"station":"Red2","dq":false,"onField":true}],"modifiedOn":"2024-11-23T23:34:18.862"},{"actualStartTime":"2024-11-23T14:40:09.048","description":"Qualification 34","tournamentLevel":"QUALIFICATION","series":0,"matchNumber":34,"scoreRedFinal":129,"scoreRedFoul":0,"scoreRedAuto":34,"scoreBlueFinal":65,"scoreBlueFoul":0,"scoreBlueAuto":3,"postResultTime":"2024-11-23T14:45:13.182","teams":[{"teamNumber":5980,"station":"Blue2","dq":false,"onField":true},{"teamNumber":20245,"station":"Red1","dq":false,"onField":true},{"teamNumber":10031,"station":"Red2","dq":false,"onField":true},{"teamNumber":20863,"station":"Blue1","dq":false,"onField":true}],"modifiedOn":"2024-11-23T23:34:18.975"},{"actualStartTime":"2024-11-23T14:45:54.665","description":"Qualification 35","tournamentLevel":"QUALIFICATION","series":0,"matchNumber":35,"scoreRedFinal":35,"scoreRedFoul":0,"scoreRedAuto":6,"scoreBlueFinal":165,"scoreBlueFoul":0,"scoreBlueAuto":33,"postResultTime":"2024-11-23T14:50:14.783","teams":[{"teamNumber":11228,"station":"Blue2","dq":false,"onField":true},{"teamNumber":11846,"station":"Blue1","dq":false,"onField":true},{"teamNumber":20299,"station":"Red2","dq":false,"onField":true},{"teamNumber":22154,"station":"Red1","dq":false,"onField":true}],"modifiedOn":"2024-11-23T23:34:19.117"},{"actualStartTime":"2024-11-23T14:57:01.505","description":"Qualification 36","tournamentLevel":"QUALIFICATION","series":0,"matchNumber":36,"scoreRedFinal":155,"scoreRedFoul":0,"scoreRedAuto":24,"scoreBlueFinal":118,"scoreBlueFoul":0,"scoreBlueAuto":24,"postResultTime":"2024-11-23T15:01:01.228","teams":[{"teamNumber":22885,"station":"Red1","dq":false,"onField":true},{"teamNumber":5290,"station":"Red2","dq":false,"onField":true},{"teamNumber":15815,"station":"Blue2","dq":false,"onField":true},{"teamNumber":23027,"station":"Blue1","dq":false,"onField":true}],"modifiedOn":"2024-11-23T23:34:19.173"},{"actualStartTime":"2024-11-23T15:01:59.675","description":"Qualification 37","tournamentLevel":"QUALIFICATION","series":0,"matchNumber":37,"scoreRedFinal":180,"scoreRedFoul":0,"scoreRedAuto":46,"scoreBlueFinal":115,"scoreBlueFoul":0,"scoreBlueAuto":23,"postResultTime":"2024-11-23T15:05:55.391","teams":[{"teamNumber":5385,"station":"Red1","dq":false,"onField":true},{"teamNumber":15510,"station":"Blue2","dq":false,"onField":true},{"teamNumber":18092,"station":"Blue1","dq":false,"onField":true},{"teamNumber":19429,"station":"Red2","dq":false,"onField":true}],"modifiedOn":"2024-11-23T23:34:18.843"},{"actualStartTime":"2024-11-23T15:06:47.379","description":"Qualification 38","tournamentLevel":"QUALIFICATION","series":0,"matchNumber":38,"scoreRedFinal":151,"scoreRedFoul":0,"scoreRedAuto":22,"scoreBlueFinal":63,"scoreBlueFoul":0,"scoreBlueAuto":5,"postResultTime":"2024-11-23T15:10:58.57","teams":[{"teamNumber":23856,"station":"Red2","dq":false,"onField":true},{"teamNumber":10255,"station":"Red1","dq":false,"onField":true},{"teamNumber":8733,"station":"Blue1","dq":false,"onField":true},{"teamNumber":8932,"station":"Blue2","dq":false,"onField":true}],"modifiedOn":"2024-11-23T23:34:18.956"},{"actualStartTime":"2024-11-23T15:12:52.938","description":"Qualification 39","tournamentLevel":"QUALIFICATION","series":0,"matchNumber":39,"scoreRedFinal":55,"scoreRedFoul":5,"scoreRedAuto":13,"scoreBlueFinal":156,"scoreBlueFoul":0,"scoreBlueAuto":23,"postResultTime":"2024-11-23T15:17:06.582","teams":[{"teamNumber":11531,"station":"Red2","dq":false,"onField":true},{"teamNumber":17401,"station":"Red1","dq":false,"onField":true},{"teamNumber":11228,"station":"Blue2","dq":false,"onField":true},{"teamNumber":10031,"station":"Blue1","dq":false,"onField":true}],"modifiedOn":"2024-11-23T23:34:19.089"},{"actualStartTime":"2024-11-23T15:17:38.693","description":"Qualification 40","tournamentLevel":"QUALIFICATION","series":0,"matchNumber":40,"scoreRedFinal":88,"scoreRedFoul":0,"scoreRedAuto":10,"scoreBlueFinal":79,"scoreBlueFoul":0,"scoreBlueAuto":9,"postResultTime":"2024-11-23T15:21:36.117","teams":[{"teamNumber":22154,"station":"Blue2","dq":false,"onField":true},{"teamNumber":11266,"station":"Blue1","dq":false,"onField":true},{"teamNumber":5980,"station":"Red2","dq":false,"onField":true},{"teamNumber":27689,"station":"Red1","dq":false,"onField":true}],"modifiedOn":"2024-11-23T23:34:19.163"},{"actualStartTime":"2024-11-23T15:22:15.913","description":"Qualification 41","tournamentLevel":"QUALIFICATION","series":0,"matchNumber":41,"scoreRedFinal":139,"scoreRedFoul":0,"scoreRedAuto":30,"scoreBlueFinal":71,"scoreBlueFoul":0,"scoreBlueAuto":3,"postResultTime":"2024-11-23T15:26:06.736","teams":[{"teamNumber":8529,"station":"Blue2","dq":false,"onField":true},{"teamNumber":24371,"station":"Red1","dq":false,"onField":true},{"teamNumber":11317,"station":"Blue1","dq":false,"onField":true},{"teamNumber":20245,"station":"Red2","dq":false,"onField":true}],"modifiedOn":"2024-11-23T23:34:18.824"},{"actualStartTime":"2024-11-23T15:26:53.623","description":"Qualification 42","tournamentLevel":"QUALIFICATION","series":0,"matchNumber":42,"scoreRedFinal":91,"scoreRedFoul":0,"scoreRedAuto":16,"scoreBlueFinal":91,"scoreBlueFoul":0,"scoreBlueAuto":13,"postResultTime":"2024-11-23T15:30:56.064","teams":[{"teamNumber":11846,"station":"Blue2","dq":false,"onField":true},{"teamNumber":10538,"station":"Blue1","dq":false,"onField":true},{"teamNumber":20863,"station":"Red2","dq":false,"onField":true},{"teamNumber":11254,"station":"Red1","dq":false,"onField":true}],"modifiedOn":"2024-11-23T23:34:18.938"},{"actualStartTime":"2024-11-23T15:32:33.567","description":"Qualification 43","tournamentLevel":"QUALIFICATION","series":0,"matchNumber":43,"scoreRedFinal":107,"scoreRedFoul":0,"scoreRedAuto":11,"scoreBlueFinal":58,"scoreBlueFoul":0,"scoreBlueAuto":0,"postResultTime":"2024-11-23T15:35:55.361","teams":[{"teamNumber":20862,"station":"Blue2","dq":false,"onField":true},{"teamNumber":6283,"station":"Blue1","dq":false,"onField":true},{"teamNumber":20299,"station":"Red2","dq":false,"onField":true},{"teamNumber":10180,"station":"Red1","dq":false,"onField":true}],"modifiedOn":"2024-11-23T23:34:19.069"},{"actualStartTime":"2024-11-23T15:44:35.359","description":"Qualification 44","tournamentLevel":"QUALIFICATION","series":0,"matchNumber":44,"scoreRedFinal":78,"scoreRedFoul":0,"scoreRedAuto":16,"scoreBlueFinal":46,"scoreBlueFoul":0,"scoreBlueAuto":13,"postResultTime":"2024-11-23T15:48:34.947","teams":[{"teamNumber":14933,"station":"Red1","dq":false,"onField":true},{"teamNumber":15339,"station":"Red2","dq":false,"onField":true},{"teamNumber":17283,"station":"Blue1","dq":false,"onField":true},{"teamNumber":15510,"station":"Blue2","dq":false,"onField":true}],"modifiedOn":"2024-11-23T23:34:19.155"},{"actualStartTime":"2024-11-23T16:47:27.781","description":"Upper Bracket  Round 1 Match 1","tournamentLevel":"PLAYOFF","series":1,"matchNumber":1,"scoreRedFinal":128,"scoreRedFoul":0,"scoreRedAuto":51,"scoreBlueFinal":37,"scoreBlueFoul":0,"scoreBlueAuto":13,"postResultTime":"2024-11-23T16:52:11.705","teams":[{"teamNumber":5290,"station":"Red1","dq":false,"onField":true},{"teamNumber":20245,"station":"Red2","dq":false,"onField":true},{"teamNumber":10031,"station":"Blue1","dq":false,"onField":true},{"teamNumber":11531,"station":"Blue2","dq":false,"onField":true}],"modifiedOn":"2024-11-23T23:34:19.21"},{"actualStartTime":"2024-11-23T16:53:50.809","description":"Upper Bracket  Round 1 Match 2","tournamentLevel":"PLAYOFF","series":2,"matchNumber":1,"scoreRedFinal":165,"scoreRedFoul":0,"scoreRedAuto":50,"scoreBlueFinal":128,"scoreBlueFoul":0,"scoreBlueAuto":21,"postResultTime":"2024-11-23T16:58:58.992","teams":[{"teamNumber":19429,"station":"Red1","dq":false,"onField":true},{"teamNumber":15815,"station":"Red2","dq":false,"onField":true},{"teamNumber":10538,"station":"Blue1","dq":false,"onField":true},{"teamNumber":11254,"station":"Blue2","dq":false,"onField":true}],"modifiedOn":"2024-11-23T23:34:19.201"},{"actualStartTime":"2024-11-23T17:00:01.267","description":"Upper Bracket  Round 2 Match 3","tournamentLevel":"PLAYOFF","series":3,"matchNumber":1,"scoreRedFinal":344,"scoreRedFoul":0,"scoreRedAuto":72,"scoreBlueFinal":170,"scoreBlueFoul":15,"scoreBlueAuto":51,"postResultTime":"2024-11-23T17:05:25.874","teams":[{"teamNumber":20245,"station":"Blue2","dq":false,"onField":true},{"teamNumber":5290,"station":"Blue1","dq":false,"onField":true},{"teamNumber":10255,"station":"Red2","dq":false,"onField":true},{"teamNumber":11228,"station":"Red1","dq":false,"onField":true}],"modifiedOn":"2024-11-23T23:34:19.258"},{"actualStartTime":"2024-11-23T17:07:16.133","description":"Upper Bracket  Round 2 Match 4","tournamentLevel":"PLAYOFF","series":4,"matchNumber":1,"scoreRedFinal":171,"scoreRedFoul":0,"scoreRedAuto":21,"scoreBlueFinal":179,"scoreBlueFoul":0,"scoreBlueAuto":28,"postResultTime":"2024-11-23T17:11:13.259","teams":[{"teamNumber":19429,"station":"Blue1","dq":false,"onField":true},{"teamNumber":15815,"station":"Blue2","dq":false,"onField":true},{"teamNumber":5385,"station":"Red2","dq":false,"onField":true},{"teamNumber":10180,"station":"Red1","dq":false,"onField":true}],"modifiedOn":"2024-11-23T23:34:19.191"},{"actualStartTime":"2024-11-23T17:14:15.844","description":"Lower Bracket  Round 3 Match 5","tournamentLevel":"PLAYOFF","series":5,"matchNumber":1,"scoreRedFinal":145,"scoreRedFoul":0,"scoreRedAuto":41,"scoreBlueFinal":98,"scoreBlueFoul":0,"scoreBlueAuto":21,"postResultTime":"2024-11-23T17:18:17.968","teams":[{"teamNumber":5290,"station":"Red1","dq":false,"onField":true},{"teamNumber":20245,"station":"Red2","dq":false,"onField":true},{"teamNumber":10538,"station":"Blue1","dq":false,"onField":true},{"teamNumber":11254,"station":"Blue2","dq":false,"onField":true}],"modifiedOn":"2024-11-23T23:34:19.239"},{"actualStartTime":"2024-11-23T17:23:21.102","description":"Lower Bracket  Round 3 Match 6","tournamentLevel":"PLAYOFF","series":6,"matchNumber":1,"scoreRedFinal":141,"scoreRedFoul":0,"scoreRedAuto":19,"scoreBlueFinal":105,"scoreBlueFoul":0,"scoreBlueAuto":13,"postResultTime":"2024-11-23T17:28:07.678","teams":[{"teamNumber":11531,"station":"Blue2","dq":false,"onField":true},{"teamNumber":10180,"station":"Red1","dq":false,"onField":true},{"teamNumber":10031,"station":"Blue1","dq":false,"onField":true},{"teamNumber":5385,"station":"Red2","dq":false,"onField":true}],"modifiedOn":"2024-11-23T23:34:19.248"},{"actualStartTime":"2024-11-23T17:29:55.171","description":"Upper Bracket  Round 4 Match 7","tournamentLevel":"PLAYOFF","series":7,"matchNumber":1,"scoreRedFinal":279,"scoreRedFoul":5,"scoreRedAuto":37,"scoreBlueFinal":226,"scoreBlueFoul":0,"scoreBlueAuto":64,"postResultTime":"2024-11-23T17:34:13.968","teams":[{"teamNumber":15815,"station":"Blue2","dq":false,"onField":true},{"teamNumber":19429,"station":"Blue1","dq":false,"onField":true},{"teamNumber":10255,"station":"Red2","dq":false,"onField":true},{"teamNumber":11228,"station":"Red1","dq":false,"onField":true}],"modifiedOn":"2024-11-23T23:34:19.267"},{"actualStartTime":"2024-11-23T17:37:22.046","description":"Lower Bracket  Round 4 Match 8","tournamentLevel":"PLAYOFF","series":8,"matchNumber":1,"scoreRedFinal":105,"scoreRedFoul":0,"scoreRedAuto":11,"scoreBlueFinal":178,"scoreBlueFoul":0,"scoreBlueAuto":41,"postResultTime":"2024-11-23T17:41:07.507","teams":[{"teamNumber":5385,"station":"Red2","dq":false,"onField":true},{"teamNumber":5290,"station":"Blue1","dq":false,"onField":true},{"teamNumber":20245,"station":"Blue2","dq":false,"onField":true},{"teamNumber":10180,"station":"Red1","dq":false,"onField":true}],"modifiedOn":"2024-11-23T23:34:19.182"},{"actualStartTime":"2024-11-23T17:55:01.092","description":"Lower Bracket  Round 5 Match 9","tournamentLevel":"PLAYOFF","series":9,"matchNumber":1,"scoreRedFinal":210,"scoreRedFoul":0,"scoreRedAuto":46,"scoreBlueFinal":146,"scoreBlueFoul":5,"scoreBlueAuto":51,"postResultTime":"2024-11-23T17:59:55.926","teams":[{"teamNumber":5290,"station":"Blue1","dq":false,"onField":true},{"teamNumber":19429,"station":"Red1","dq":false,"onField":true},{"teamNumber":20245,"station":"Blue2","dq":false,"onField":true},{"teamNumber":15815,"station":"Red2","dq":false,"onField":true}],"modifiedOn":"2024-11-23T23:34:19.22"},{"actualStartTime":"2024-11-23T18:12:05.916","description":"Final Bracket  Round 6 Match 10","tournamentLevel":"PLAYOFF","series":10,"matchNumber":1,"scoreRedFinal":294,"scoreRedFoul":0,"scoreRedAuto":52,"scoreBlueFinal":161,"scoreBlueFoul":0,"scoreBlueAuto":44,"postResultTime":"2024-11-23T18:15:52.858","teams":[{"teamNumber":10255,"station":"Red2","dq":false,"onField":true},{"teamNumber":19429,"station":"Blue1","dq":false,"onField":true},{"teamNumber":11228,"station":"Red1","dq":false,"onField":true},{"teamNumber":15815,"station":"Blue2","dq":false,"onField":true}],"modifiedOn":"2024-11-23T23:34:19.229"}]}