{
  "winProbability": 0.607524460615413,
  "predictedWinner": "Red",
  "redTeams": [
    27030,
    26268
  ],
  "blueTeams": [
    15722,
    8027
  ],
  "actualWinner": "Red",
  "pointBreakdown": {
    "redData": {
      "redScore": 109,
      "redPenaltyFreeScore": 74,
      "redAuto": 16,
      "redTeleOp": 48,
      "redEndgame": 10
    },
    "blueData": {
      "blueScore": 88,
      "bluePenaltyFreeScore": 88,
      "blueAuto": 27,
      "blueTeleOp": 51,
      "blueEndgame": 10
    }
  },
  "predictedScores": {
    "redEPA": 64.13611698217538,
    "redAutonEPA": 13.609817170641847,
    "redTeleOpEPA": 40.82781018760478,
    "redEndgameEPA": 9.698489623928754,
    "blueEPA": 53.86789669801644,
    "blueAutonEPA": 13.894517123835127,
    "blueTeleOpEPA": 27.6554363221893,
    "blueEndgameEPA": 12.31794325199201
  }
}