{
  "winProbability": 0.5999297500352097,
  "predictedWinner": "Red",
  "redTeams": [
    22302,
    27587
  ],
  "blueTeams": [
    27586,
    25093
  ],
  "actualWinner": "Blue",
  "pointBreakdown": {
    "redData": {
      "redScore": 74,
      "redPenaltyFreeScore": 54,
      "redAuto": 14,
      "redTeleOp": 35,
      "redEndgame": 5
    },
    "blueData": {
      "blueScore": 131,
      "bluePenaltyFreeScore": 101,
      "blueAuto": 19,
      "blueTeleOp": 52,
      "blueEndgame": 30
    }
  },
  "predictedScores": {
    "redEPA": 74.65059858313133,
    "redAutonEPA": 16.762925901265973,
    "redTeleOpEPA": 42.35500728406847,
    "redEndgameEPA": 15.532665397796881,
    "blueEPA": 64.34449626905256,
    "blueAutonEPA": 17.879310730698258,
    "blueTeleOpEPA": 33.597489507064935,
    "blueEndgameEPA": 12.867696031289364
  }
}