{
  "predictedWinner": "Blue",
  "redTeams": [
    20895,
    20892
  ],
  "blueTeams": [
    20894,
    20897
  ],
  "actualWinner": "Blue",
  "pointBreakdown": {
    "redData": {
      "redScore": 26,
      "redPenaltyFreeScore": 26,
      "redAuto": 0,
      "redTeleOp": 26,
      "redEndgame": null
    },
    "blueData": {
      "blueScore": 39,
      "bluePenaltyFreeScore": 39,
      "blueAuto": 0,
      "blueTeleOp": 39,
      "blueEndgame": null
    }
  },
  "predictedScores": {
    "redEPA": 19.96489871802778,
    "redAutonEPA": 0.15260157112355677,
    "redTeleOpEPA": 19.81229714690422,
    "redEndgameEPA": 0,
    "blueEPA": 34.73030580363075,
    "blueAutonEPA": -0.09701181549568715,
    "blueTeleOpEPA": 34.82731761912643,
    "blueEndgameEPA": 0
  }
}