{
  "predictedWinner": "Red",
  "redTeams": [
    8492,
    32285
  ],
  "blueTeams": [
    28804,
    26538
  ],
  "actualWinner": "Blue",
  "pointBreakdown": {
    "redData": {
      "redScore": 75,
      "redPenaltyFreeScore": 70,
      "redAuto": 16,
      "redTeleOp": 54,
      "redEndgame": 0
    },
    "blueData": {
      "blueScore": 116,
      "bluePenaltyFreeScore": 116,
      "blueAuto": 48,
      "blueTeleOp": 68,
      "blueEndgame": 0
    }
  },
  "predictedScores": {
    "redEPA": 67.42006234683905,
    "redAutonEPA": 8.173834469395626,
    "redTeleOpEPA": 51.97234283098853,
    "redEndgameEPA": 7.273885046454886,
    "blueEPA": 40.516150263752145,
    "blueAutonEPA": 22.737083663129717,
    "blueTeleOpEPA": 11.774160119769068,
    "blueEndgameEPA": 6.00490648085336
  }
}