{
  "winProbability": 0.9412691221387732,
  "predictedWinner": "Blue",
  "redTeams": [
    22415,
    22134
  ],
  "blueTeams": [
    7693,
    10016
  ],
  "actualWinner": "Blue",
  "pointBreakdown": {
    "redData": {
      "redScore": 56,
      "redPenaltyFreeScore": 41,
      "redAuto": 3,
      "redTeleOp": 23,
      "redEndgame": 15
    },
    "blueData": {
      "blueScore": 157,
      "bluePenaltyFreeScore": 157,
      "blueAuto": 51,
      "blueTeleOp": 91,
      "blueEndgame": 15
    }
  },
  "predictedScores": {
    "redEPA": 71.53300564627847,
    "redAutonEPA": 13.400449740786176,
    "redTeleOpEPA": 44.15668939295399,
    "redEndgameEPA": 13.975866512538303,
    "blueEPA": 151.51473515675264,
    "blueAutonEPA": 48.823669700781096,
    "blueTeleOpEPA": 87.21733473580883,
    "blueEndgameEPA": 15.473730720162699
  }
}