{
  "winProbability": 0.5163765898184912,
  "predictedWinner": "Blue",
  "redTeams": [
    25085,
    25089
  ],
  "blueTeams": [
    25087,
    25084
  ],
  "actualWinner": "Blue",
  "pointBreakdown": {
    "redData": {
      "redScore": 39,
      "redPenaltyFreeScore": 39,
      "redAuto": 6,
      "redTeleOp": 18,
      "redEndgame": 15
    },
    "blueData": {
      "blueScore": 42,
      "bluePenaltyFreeScore": 42,
      "blueAuto": 10,
      "blueTeleOp": 17,
      "blueEndgame": 15
    }
  },
  "predictedScores": {
    "redEPA": 30.231065338156544,
    "redAutonEPA": 8.26351587523948,
    "redTeleOpEPA": 16.079862701448906,
    "redEndgameEPA": 5.887686761468156,
    "blueEPA": 31.880380013387118,
    "blueAutonEPA": 6.030354003743749,
    "blueTeleOpEPA": 17.338298531956735,
    "blueEndgameEPA": 8.511727477686634
  }
}