{
  "predictedWinner": "Blue",
  "redTeams": [
    11729,
    9297
  ],
  "blueTeams": [
    13667,
    15191
  ],
  "actualWinner": "Red",
  "pointBreakdown": {
    "redData": {
      "redScore": 81,
      "redPenaltyFreeScore": 71,
      "redAuto": 16,
      "redTeleOp": -4,
      "redEndgame": 59
    },
    "blueData": {
      "blueScore": 45,
      "bluePenaltyFreeScore": 45,
      "blueAuto": 6,
      "blueTeleOp": 6,
      "blueEndgame": 33
    }
  },
  "predictedScores": {
    "redEPA": 22.246271878386302,
    "redAutonEPA": 12.81355980289343,
    "redTeleOpEPA": -1.43205571397068,
    "redEndgameEPA": 10.864767789463553,
    "blueEPA": 72.76094834712217,
    "blueAutonEPA": 17.190405094786154,
    "blueTeleOpEPA": 3.2069222437680907,
    "blueEndgameEPA": 52.36362100856792
  }
}