{
  "predictedWinner": "Blue",
  "redTeams": [
    8603,
    24253
  ],
  "blueTeams": [
    23606,
    30453
  ],
  "actualWinner": "Red",
  "pointBreakdown": {
    "redData": {
      "redScore": 108,
      "redPenaltyFreeScore": 103,
      "redAuto": 19,
      "redTeleOp": 84,
      "redEndgame": 0
    },
    "blueData": {
      "blueScore": 58,
      "bluePenaltyFreeScore": 43,
      "blueAuto": 16,
      "blueTeleOp": 27,
      "blueEndgame": 0
    }
  },
  "predictedScores": {
    "redEPA": 35.66596358648165,
    "redAutonEPA": 4.959813108989007,
    "redTeleOpEPA": 21.363626198003114,
    "redEndgameEPA": 9.342524279489531,
    "blueEPA": 56.53344337868947,
    "blueAutonEPA": 10.534160392146152,
    "blueTeleOpEPA": 38.67285610038347,
    "blueEndgameEPA": 7.326426886159852
  }
}