{
  "winProbability": 0.9229584578830805,
  "predictedWinner": "Red",
  "redTeams": [
    24253,
    13684
  ],
  "blueTeams": [
    17349,
    12085
  ],
  "actualWinner": "Red",
  "pointBreakdown": {
    "redData": {
      "redScore": 116,
      "redPenaltyFreeScore": 116,
      "redAuto": 31,
      "redTeleOp": 70,
      "redEndgame": 15
    },
    "blueData": {
      "blueScore": 53,
      "bluePenaltyFreeScore": 53,
      "blueAuto": 16,
      "blueTeleOp": 22,
      "blueEndgame": 15
    }
  },
  "predictedScores": {
    "redEPA": 110.62612853693835,
    "redAutonEPA": 28.682167184571554,
    "redTeleOpEPA": 64.91786230239364,
    "redEndgameEPA": 17.026099049973148,
    "blueEPA": 54.1591443846186,
    "blueAutonEPA": 15.4399537782918,
    "blueTeleOpEPA": 27.19774460318167,
    "blueEndgameEPA": 11.521446003145128
  }
}