{
  "predictedWinner": "Red",
  "redTeams": [
    14010,
    8478
  ],
  "blueTeams": [
    12811,
    11717
  ],
  "actualWinner": "Red",
  "pointBreakdown": {
    "redData": {
      "redScore": 156,
      "redPenaltyFreeScore": 126,
      "redAuto": 68,
      "redTeleOp": 2,
      "redEndgame": 56
    },
    "blueData": {
      "blueScore": 0,
      "bluePenaltyFreeScore": -90,
      "blueAuto": 16,
      "blueTeleOp": -124,
      "blueEndgame": 18
    }
  },
  "predictedScores": {
    "redEPA": 137.1613984147521,
    "redAutonEPA": 27.544808475741682,
    "redTeleOpEPA": 60.655975111846814,
    "redEndgameEPA": 48.96061482716361,
    "blueEPA": 62.32581468030576,
    "blueAutonEPA": 34.396010167461306,
    "blueTeleOpEPA": -50.05878644901156,
    "blueEndgameEPA": 77.98859096185602
  }
}