{
  "predictedWinner": "Blue",
  "redTeams": [
    16297,
    12440
  ],
  "blueTeams": [
    15835,
    11181
  ],
  "actualWinner": "Blue",
  "pointBreakdown": {
    "redData": {
      "redScore": 17,
      "redPenaltyFreeScore": -43,
      "redAuto": 48,
      "redTeleOp": -100,
      "redEndgame": 9
    },
    "blueData": {
      "blueScore": 116,
      "bluePenaltyFreeScore": 116,
      "blueAuto": 29,
      "blueTeleOp": 36,
      "blueEndgame": 51
    }
  },
  "predictedScores": {
    "redEPA": 82.12680968228119,
    "redAutonEPA": 41.14881345693704,
    "redTeleOpEPA": 18.334712364528222,
    "redEndgameEPA": 22.643283860815927,
    "blueEPA": 133.9038051951745,
    "blueAutonEPA": 34.03510212201744,
    "blueTeleOpEPA": 54.39747033670889,
    "blueEndgameEPA": 45.47123273644817
  }
}