{
  "predictedWinner": "Red",
  "redTeams": [
    14791,
    20332
  ],
  "blueTeams": [
    13002,
    12549
  ],
  "actualWinner": "Red",
  "pointBreakdown": {
    "redData": {
      "redScore": 135,
      "redPenaltyFreeScore": 125,
      "redAuto": 13,
      "redTeleOp": 112,
      "redEndgame": null
    },
    "blueData": {
      "blueScore": 50,
      "bluePenaltyFreeScore": 50,
      "blueAuto": 8,
      "blueTeleOp": 42,
      "blueEndgame": null
    }
  },
  "predictedScores": {
    "redEPA": 73.87148364011202,
    "redAutonEPA": 19.698718614603813,
    "redTeleOpEPA": 54.172765025508205,
    "redEndgameEPA": 0,
    "blueEPA": 21.1375,
    "blueAutonEPA": 1.875,
    "blueTeleOpEPA": 19.2625,
    "blueEndgameEPA": 0
  }
}