{
  "predictedWinner": "Red",
  "redTeams": [
    15182,
    11769
  ],
  "blueTeams": [
    5237,
    14351
  ],
  "actualWinner": "Blue",
  "pointBreakdown": {
    "redData": {
      "redScore": 57,
      "redPenaltyFreeScore": 57,
      "redAuto": 5,
      "redTeleOp": 52
    },
    "blueData": {
      "blueScore": 57,
      "bluePenaltyFreeScore": 57,
      "blueAuto": 25,
      "blueTeleOp": 32
    }
  },
  "predictedScores": {
    "redEPA": 66.82085925923852,
    "redAutonEPA": 22.643701972805694,
    "redTeleOpEPA": 44.17715728643282,
    "blueEPA": 36.12823476741818,
    "blueAutonEPA": 19.942632430535586,
    "blueTeleOpEPA": 16.185602336882592
  }
}