{
  "predictedWinner": "Blue",
  "redTeams": [
    11618,
    14670
  ],
  "blueTeams": [
    11729,
    13647
  ],
  "actualWinner": "Red",
  "pointBreakdown": {
    "redData": {
      "redScore": 57,
      "redPenaltyFreeScore": 27,
      "redAuto": 29,
      "redTeleOp": -34,
      "redEndgame": 32
    },
    "blueData": {
      "blueScore": 24,
      "bluePenaltyFreeScore": 24,
      "blueAuto": 9,
      "blueTeleOp": 2,
      "blueEndgame": 13
    }
  },
  "predictedScores": {
    "redEPA": 20.803965471968596,
    "redAutonEPA": 22.837838283945874,
    "redTeleOpEPA": -4.321756779444546,
    "redEndgameEPA": 2.287883967467267,
    "blueEPA": 68.10004395025526,
    "blueAutonEPA": 2.059420556029191,
    "blueTeleOpEPA": 27.33468229081862,
    "blueEndgameEPA": 38.70594110340744
  }
}