{
  "predictedWinner": "Red",
  "redTeams": [
    15119,
    8142
  ],
  "blueTeams": [
    27562,
    15191
  ],
  "actualWinner": "Red",
  "pointBreakdown": {
    "redData": {
      "redScore": 120,
      "redPenaltyFreeScore": 105,
      "redAuto": 35,
      "redTeleOp": 70,
      "redEndgame": 0
    },
    "blueData": {
      "blueScore": 66,
      "bluePenaltyFreeScore": 66,
      "blueAuto": 13,
      "blueTeleOp": 43,
      "blueEndgame": 10
    }
  },
  "predictedScores": {
    "redEPA": 87.68425354372995,
    "redAutonEPA": 22.257735462207513,
    "redTeleOpEPA": 60.878127854959935,
    "redEndgameEPA": 4.548390226562494,
    "blueEPA": 42.065945051235545,
    "blueAutonEPA": 11.325393311437487,
    "blueTeleOpEPA": 25.644054087413508,
    "blueEndgameEPA": 5.096497652384549
  }
}