{
  "predictedWinner": "Blue",
  "redTeams": [
    15229,
    11244
  ],
  "blueTeams": [
    10538,
    22420
  ],
  "actualWinner": "Red",
  "pointBreakdown": {
    "redData": {
      "redScore": 168,
      "redPenaltyFreeScore": 148,
      "redAuto": 35,
      "redTeleOp": 82,
      "redEndgame": 31
    },
    "blueData": {
      "blueScore": 137,
      "bluePenaltyFreeScore": 117,
      "blueAuto": 40,
      "blueTeleOp": 43,
      "blueEndgame": 34
    }
  },
  "predictedScores": {
    "redEPA": 28.883333333333333,
    "redAutonEPA": 5.333333333333333,
    "redTeleOpEPA": 15.766666666666667,
    "redEndgameEPA": 7.783333333333333,
    "blueEPA": 33.85246908885294,
    "blueAutonEPA": 9.456654779922275,
    "blueTeleOpEPA": 15.810097579397627,
    "blueEndgameEPA": 8.58571672953304
  }
}