{
  "predictedWinner": "Red",
  "redTeams": [
    16646,
    5385,
    19693
  ],
  "blueTeams": [
    8492,
    13917,
    9476
  ],
  "actualWinner": "Red",
  "pointBreakdown": {
    "redData": {
      "redScore": 286,
      "redPenaltyFreeScore": 286,
      "redAuto": 68,
      "redTeleOp": 114,
      "redEndgame": 104
    },
    "blueData": {
      "blueScore": 220,
      "bluePenaltyFreeScore": 220,
      "blueAuto": 65,
      "blueTeleOp": 92,
      "blueEndgame": 63
    }
  },
  "predictedScores": {
    "redEPA": 356.1289614885162,
    "redAutonEPA": 97.8937438492833,
    "redTeleOpEPA": 100.90472057753107,
    "redEndgameEPA": 157.33049706170186,
    "blueEPA": 345.04766339045756,
    "blueAutonEPA": 99.45338930803551,
    "blueTeleOpEPA": 117.48601010895987,
    "blueEndgameEPA": 128.10826397346216
  }
}