{
  "predictedWinner": "Blue",
  "redTeams": [
    11846,
    17207
  ],
  "blueTeams": [
    8492,
    5386
  ],
  "actualWinner": "Blue",
  "pointBreakdown": {
    "redData": {
      "redScore": 78,
      "redPenaltyFreeScore": 78,
      "redAuto": 16,
      "redTeleOp": 22,
      "redEndgame": 40
    },
    "blueData": {
      "blueScore": 266,
      "bluePenaltyFreeScore": 266,
      "blueAuto": 75,
      "blueTeleOp": 90,
      "blueEndgame": 101
    }
  },
  "predictedScores": {
    "redEPA": 125.5377936292836,
    "redAutonEPA": 19.661037392419594,
    "redTeleOpEPA": 19.44438451002668,
    "redEndgameEPA": 86.43237172683732,
    "blueEPA": 256.816092245989,
    "blueAutonEPA": 34.13317425377838,
    "blueTeleOpEPA": 104.19106290317269,
    "blueEndgameEPA": 118.49185508903794
  }
}