{
  "predictedWinner": "Red",
  "redTeams": [
    24371,
    20245
  ],
  "blueTeams": [
    11317,
    8529
  ],
  "actualWinner": "Red",
  "pointBreakdown": {
    "redData": {
      "redScore": 139,
      "redPenaltyFreeScore": 139,
      "redAuto": 30,
      "redTeleOp": 109,
      "redEndgame": null
    },
    "blueData": {
      "blueScore": 71,
      "bluePenaltyFreeScore": 71,
      "blueAuto": 3,
      "blueTeleOp": 68,
      "blueEndgame": null
    }
  },
  "predictedScores": {
    "redEPA": 88.68960177958323,
    "redAutonEPA": 13.23167618419396,
    "redTeleOpEPA": 75.45792559538927,
    "redEndgameEPA": 0,
    "blueEPA": 6.494094337665352,
    "blueAutonEPA": 1.6329610177796832,
    "blueTeleOpEPA": 4.861133319885669,
    "blueEndgameEPA": 0
  }
}