{
  "predictedWinner": "Blue",
  "redTeams": [
    8580,
    14706,
    10477
  ],
  "blueTeams": [
    10615,
    8533,
    15814
  ],
  "actualWinner": "Blue",
  "pointBreakdown": {
    "redData": {
      "redScore": 151,
      "redPenaltyFreeScore": 141,
      "redAuto": 51,
      "redTeleOp": 28,
      "redEndgame": 62
    },
    "blueData": {
      "blueScore": 176,
      "bluePenaltyFreeScore": 176,
      "blueAuto": 68,
      "blueTeleOp": 60,
      "blueEndgame": 48
    }
  },
  "predictedScores": {
    "redEPA": 241.09239398098396,
    "redAutonEPA": 70.61305022995958,
    "redTeleOpEPA": 78.13114852518783,
    "redEndgameEPA": 92.34819522583655,
    "blueEPA": 263.8143738345798,
    "blueAutonEPA": 65.17739389617267,
    "blueTeleOpEPA": 87.02061266786446,
    "blueEndgameEPA": 111.61636727054265
  }
}