{
  "predictedWinner": "Blue",
  "redTeams": [
    24360,
    8027
  ],
  "blueTeams": [
    15465,
    21340
  ],
  "actualWinner": "Blue",
  "pointBreakdown": {
    "redData": {
      "redScore": 61,
      "redPenaltyFreeScore": 61,
      "redAuto": 0,
      "redTeleOp": 16,
      "redEndgame": 45
    },
    "blueData": {
      "blueScore": 129,
      "bluePenaltyFreeScore": 129,
      "blueAuto": 80,
      "blueTeleOp": 9,
      "blueEndgame": 40
    }
  },
  "predictedScores": {
    "redEPA": 50.87567281607265,
    "redAutonEPA": 41.04192559692259,
    "redTeleOpEPA": -3.899786532501249,
    "redEndgameEPA": 13.733533751651311,
    "blueEPA": 185.36492955474003,
    "blueAutonEPA": 67.98374731994558,
    "blueTeleOpEPA": 44.12273979731626,
    "blueEndgameEPA": 73.2584424374782
  }
}