{
  "predictedWinner": "Blue",
  "redTeams": [
    20294,
    21340
  ],
  "blueTeams": [
    19940,
    14638
  ],
  "actualWinner": "Blue",
  "pointBreakdown": {
    "redData": {
      "redScore": 85,
      "redPenaltyFreeScore": 85,
      "redAuto": 40,
      "redTeleOp": 40,
      "redEndgame": 5
    },
    "blueData": {
      "blueScore": 94,
      "bluePenaltyFreeScore": 94,
      "blueAuto": 0,
      "blueTeleOp": 66,
      "blueEndgame": 28
    }
  },
  "predictedScores": {
    "redEPA": 81.87402415537238,
    "redAutonEPA": 22.689203501379346,
    "redTeleOpEPA": 34.52226445521677,
    "redEndgameEPA": 24.662556198776265,
    "blueEPA": 85.52010265390922,
    "blueAutonEPA": 28.095088702895307,
    "blueTeleOpEPA": 33.28571403775045,
    "blueEndgameEPA": 24.139299913263457
  }
}