{
  "winProbability": 0.8509469291193054,
  "predictedWinner": "Red",
  "redTeams": [
    17975,
    7140
  ],
  "blueTeams": [
    7045,
    22537
  ],
  "actualWinner": "Red",
  "pointBreakdown": {
    "redData": {
      "redScore": 162,
      "redPenaltyFreeScore": 132,
      "redAuto": 47,
      "redTeleOp": 80,
      "redEndgame": 5
    },
    "blueData": {
      "blueScore": 86,
      "bluePenaltyFreeScore": 86,
      "blueAuto": 14,
      "blueTeleOp": 57,
      "blueEndgame": 15
    }
  },
  "predictedScores": {
    "redEPA": 116.53005498832061,
    "redAutonEPA": 32.9511842792428,
    "redTeleOpEPA": 69.89195956085088,
    "redEndgameEPA": 13.686911148226939,
    "blueEPA": 64.53152127130492,
    "blueAutonEPA": 17.65652331947487,
    "blueTeleOpEPA": 36.69452417325799,
    "blueEndgameEPA": 10.180473778572068
  }
}