{
  "winProbability": 0.7254343867650968,
  "predictedWinner": "Red",
  "redTeams": [
    21615,
    19787
  ],
  "blueTeams": [
    22373,
    13999
  ],
  "actualWinner": "Red",
  "pointBreakdown": {
    "redData": {
      "redScore": 98,
      "redPenaltyFreeScore": 98,
      "redAuto": 44,
      "redTeleOp": 44,
      "redEndgame": 10
    },
    "blueData": {
      "blueScore": 42,
      "bluePenaltyFreeScore": 42,
      "blueAuto": 11,
      "blueTeleOp": 21,
      "blueEndgame": 10
    }
  },
  "predictedScores": {
    "redEPA": 64.51435813359738,
    "redAutonEPA": 19.9927721786617,
    "redTeleOpEPA": 32.45326648015674,
    "redEndgameEPA": 12.06831947477895,
    "blueEPA": 40.966423103498805,
    "blueAutonEPA": 7.11188562597394,
    "blueTeleOpEPA": 23.16751381087607,
    "blueEndgameEPA": 10.687023666648795
  }
}