{
  "predictedWinner": "Red",
  "redTeams": [
    10180,
    10615
  ],
  "blueTeams": [
    15104,
    10104
  ],
  "actualWinner": "Red",
  "pointBreakdown": {
    "redData": {
      "redScore": 158,
      "redPenaltyFreeScore": 158,
      "redAuto": 49,
      "redTeleOp": 93,
      "redEndgame": 16
    },
    "blueData": {
      "blueScore": 154,
      "bluePenaltyFreeScore": 134,
      "blueAuto": 60,
      "blueTeleOp": 50,
      "blueEndgame": 24
    }
  },
  "predictedScores": {
    "redEPA": 216.13444701528533,
    "redAutonEPA": 32.11756143692306,
    "redTeleOpEPA": 150.29975466927505,
    "redEndgameEPA": 33.71713090908723,
    "blueEPA": 138.5465812952685,
    "blueAutonEPA": 39.51245761626294,
    "blueTeleOpEPA": 80.17385744835678,
    "blueEndgameEPA": 18.86026623064879
  }
}