{
  "predictedWinner": "Blue",
  "redTeams": [
    13106,
    22307
  ],
  "blueTeams": [
    13733,
    11129
  ],
  "actualWinner": "Blue",
  "pointBreakdown": {
    "redData": {
      "redScore": 117,
      "redPenaltyFreeScore": 107,
      "redAuto": 22,
      "redTeleOp": 61,
      "redEndgame": 24
    },
    "blueData": {
      "blueScore": 197,
      "bluePenaltyFreeScore": 197,
      "blueAuto": 56,
      "blueTeleOp": 114,
      "blueEndgame": 27
    }
  },
  "predictedScores": {
    "redEPA": 82.98786608561142,
    "redAutonEPA": 9.03482090768333,
    "redTeleOpEPA": 50.76271375182312,
    "redEndgameEPA": 23.19033142610497,
    "blueEPA": 190.39178463779206,
    "blueAutonEPA": 45.060410809189996,
    "blueTeleOpEPA": 117.72569439257782,
    "blueEndgameEPA": 27.605679436024243
  }
}