{
  "predictedWinner": "Blue",
  "redTeams": [
    13513,
    14229
  ],
  "blueTeams": [
    16204,
    11855
  ],
  "actualWinner": "Red",
  "pointBreakdown": {
    "redData": {
      "redScore": 33,
      "redPenaltyFreeScore": 33,
      "redAuto": 10,
      "redTeleOp": 8,
      "redEndgame": 15
    },
    "blueData": {
      "blueScore": 29,
      "bluePenaltyFreeScore": 29,
      "blueAuto": 5,
      "blueTeleOp": 9,
      "blueEndgame": 15
    }
  },
  "predictedScores": {
    "redEPA": 38.4766185155368,
    "redAutonEPA": 7.250701821589905,
    "redTeleOpEPA": 19.687832440806805,
    "redEndgameEPA": 11.538084253140088,
    "blueEPA": 57.31832986548999,
    "blueAutonEPA": 22.723648548673868,
    "blueTeleOpEPA": 22.251425012326568,
    "blueEndgameEPA": 12.343256304489554
  }
}