{
  "predictedWinner": "Red",
  "redTeams": [
    8734,
    20102
  ],
  "blueTeams": [
    11729,
    9895
  ],
  "actualWinner": "Red",
  "pointBreakdown": {
    "redData": {
      "redScore": 114,
      "redPenaltyFreeScore": 114,
      "redAuto": 26,
      "redTeleOp": 26,
      "redEndgame": 62
    },
    "blueData": {
      "blueScore": 98,
      "bluePenaltyFreeScore": 98,
      "blueAuto": 29,
      "blueTeleOp": 18,
      "blueEndgame": 51
    }
  },
  "predictedScores": {
    "redEPA": 128.44158195088664,
    "redAutonEPA": 24.88308965984005,
    "redTeleOpEPA": 31.76586352128787,
    "redEndgameEPA": 71.79262876975872,
    "blueEPA": 92.71789559173965,
    "blueAutonEPA": 38.000759843141886,
    "blueTeleOpEPA": 9.971930464624648,
    "blueEndgameEPA": 44.745205283973114
  }
}