{
  "predictedWinner": "Blue",
  "redTeams": [
    19949,
    16734
  ],
  "blueTeams": [
    15078,
    8478
  ],
  "actualWinner": "Blue",
  "pointBreakdown": {
    "redData": {
      "redScore": 82,
      "redPenaltyFreeScore": 72,
      "redAuto": 16,
      "redTeleOp": 14,
      "redEndgame": 42
    },
    "blueData": {
      "blueScore": 131,
      "bluePenaltyFreeScore": 121,
      "blueAuto": 65,
      "blueTeleOp": 26,
      "blueEndgame": 30
    }
  },
  "predictedScores": {
    "redEPA": 157.27607396144793,
    "redAutonEPA": 35.11264595554816,
    "redTeleOpEPA": 53.12445351565452,
    "redEndgameEPA": 69.03897449024525,
    "blueEPA": 178.1714488385013,
    "blueAutonEPA": 66.5486406078668,
    "blueTeleOpEPA": 39.86287659244714,
    "blueEndgameEPA": 71.75993163818737
  }
}